fivcplayground/__init__.py
fivcplayground/cli.py
fivcplayground/agents/__init__.py
fivcplayground/agents/types/__init__.py
fivcplayground/agents/types/base.py
fivcplayground/agents/types/repositories/__init__.py
fivcplayground/agents/types/repositories/base.py
fivcplayground/agents/types/repositories/files.py
fivcplayground/agents/types/repositories/sqlite.py
fivcplayground/backends/__init__.py
fivcplayground/backends/chroma.py
fivcplayground/backends/faiss.py
fivcplayground/backends/langchain/__init__.py
fivcplayground/backends/langchain/agents.py
fivcplayground/backends/langchain/models.py
fivcplayground/backends/langchain/tools.py
fivcplayground/backends/strands/__init__.py
fivcplayground/backends/strands/agents.py
fivcplayground/backends/strands/models.py
fivcplayground/backends/strands/tools.py
fivcplayground/demos/__init__.py
fivcplayground/demos/components/__init__.py
fivcplayground/demos/components/chat_message.py
fivcplayground/demos/components/task_message.py
fivcplayground/demos/utils/__init__.py
fivcplayground/demos/utils/chats.py
fivcplayground/demos/views/__init__.py
fivcplayground/demos/views/base.py
fivcplayground/demos/views/chats.py
fivcplayground/demos/views/tasks.py
fivcplayground/embeddings/__init__.py
fivcplayground/embeddings/types/__init__.py
fivcplayground/embeddings/types/base.py
fivcplayground/embeddings/types/repositories/__init__.py
fivcplayground/embeddings/types/repositories/base.py
fivcplayground/embeddings/types/repositories/files.py
fivcplayground/models/__init__.py
fivcplayground/models/types/__init__.py
fivcplayground/models/types/base.py
fivcplayground/models/types/repositories/__init__.py
fivcplayground/models/types/repositories/base.py
fivcplayground/models/types/repositories/files.py
fivcplayground/models/types/repositories/sqlite.py
fivcplayground/tasks/__init__.py
fivcplayground/tasks/types/__init__.py
fivcplayground/tasks/types/base.py
fivcplayground/tasks/types/repositories/__init__.py
fivcplayground-0.1.12.dist-info/METADATA
fivcplayground-0.1.12.dist-info/WHEEL
fivcplayground-0.1.12.dist-info/entry_points.txt
fivcplayground-0.1.12.dist-info/top_level.txt
fivcplayground-0.1.12.dist-info/RECORD
