Metadata-Version: 2.4
Name: fivcplayground
Version: 0.1.12
Summary: Personal Simple Generic Agents
Author-email: Charlie ZHANG <sunnypig2002@gmail.com>
License: MIT
Requires-Python: >=3.10
Requires-Dist: typer>=0.12.3
Requires-Dist: rich>=13.7.1
Requires-Dist: PyYAML>=6.0.1
Requires-Dist: python-dotenv>=1.0.1
Requires-Dist: pydantic>=2.7.0
Requires-Dist: streamlit>=1.49.1
Requires-Dist: chromadb>=1.1.0
Requires-Dist: langchain>=1.2.0
Requires-Dist: langchain-core>=1.2.0
Requires-Dist: langchain-community>=0.4.1
Requires-Dist: langchain-openai>=1.0.0
Requires-Dist: langgraph>=1.0.5
Requires-Dist: langchain-mcp-adapters>=0.2.1
Requires-Dist: langchain-ollama>=1.0.0
Requires-Dist: nest-asyncio>=1.6.0
Requires-Dist: strands-agents>=1.20.0
Requires-Dist: langchain-text-splitters>=0.3.11
Requires-Dist: httpx>=0.28.1
Requires-Dist: openai>=1.109.1
Provides-Extra: dev
Requires-Dist: pytest>=8.2.0; extra == "dev"
Requires-Dist: pytest-asyncio>=0.21.0; extra == "dev"
Requires-Dist: pytest-cov>=4.1.0; extra == "dev"
Requires-Dist: pytest-benchmark>=5.1.0; extra == "dev"
Requires-Dist: ruff<0.6,>=0.4.0; extra == "dev"
Requires-Dist: build>=1.0.0; extra == "dev"
Requires-Dist: twine>=4.0.0; extra == "dev"
